streamsightv2/__init__.py
streamsightv2/algorithms/__init__.py
streamsightv2/algorithms/base.py
streamsightv2/algorithms/decay_popularity.py
streamsightv2/algorithms/itemknn.py
streamsightv2/algorithms/itemknn_incremental.py
streamsightv2/algorithms/itemknn_incremental_movielens.py
streamsightv2/algorithms/itemknn_rolling.py
streamsightv2/algorithms/itemknn_static.py
streamsightv2/algorithms/most_pop.py
streamsightv2/algorithms/random.py
streamsightv2/algorithms/recent_popularity.py
streamsightv2/algorithms/time_aware_item_knn/__init__.py
streamsightv2/algorithms/time_aware_item_knn/base.py
streamsightv2/algorithms/time_aware_item_knn/ding_2005.py
streamsightv2/algorithms/time_aware_item_knn/liu_2010.py
streamsightv2/algorithms/time_aware_item_knn/vaz_2013.py
streamsightv2/algorithms/utils.py
streamsightv2/datasets/__init__.py
streamsightv2/datasets/amazon.py
streamsightv2/datasets/base.py
streamsightv2/datasets/lastfm.py
streamsightv2/datasets/movielens.py
streamsightv2/datasets/test.py
streamsightv2/datasets/yelp.py
streamsightv2/evaluators/__init__.py
streamsightv2/evaluators/accumulator.py
streamsightv2/evaluators/base.py
streamsightv2/evaluators/evaluator_builder.py
streamsightv2/evaluators/evaluator_pipeline.py
streamsightv2/evaluators/evaluator_stream.py
streamsightv2/evaluators/util.py
streamsightv2/matrix/__init__.py
streamsightv2/matrix/exception.py
streamsightv2/matrix/interaction_matrix.py
streamsightv2/matrix/util.py
streamsightv2/metadata/__init__.py
streamsightv2/metadata/amazon.py
streamsightv2/metadata/base.py
streamsightv2/metadata/lastfm.py
streamsightv2/metadata/movielens.py
streamsightv2/metrics/__init__.py
streamsightv2/metrics/base.py
streamsightv2/metrics/dcg.py
streamsightv2/metrics/hit.py
streamsightv2/metrics/ndcg.py
streamsightv2/metrics/precision.py
streamsightv2/metrics/recall.py
streamsightv2/metrics/util.py
streamsightv2/preprocessing/__init__.py
streamsightv2/preprocessing/filter.py
streamsightv2/preprocessing/preprocessor.py
streamsightv2-1.0.0.dist-info/LICENSE
streamsightv2-1.0.0.dist-info/METADATA
streamsightv2-1.0.0.dist-info/WHEEL
streamsightv2-1.0.0.dist-info/RECORD
