Metadata-Version: 2.1
Name: streamsightv2
Version: 1.0.0
Summary: A toolkit for offline evaluation of Recommender Systems.
Home-page: https://github.com/suenalaba/streamsightv2
Keywords: recsys,recommendation,practical evaluation,global timeline,reccomender systems,data leakage
Author: Joshua Khoo
Author-email: joshuajr13@gmail.com
Requires-Python: ==3.12.5
Classifier: Programming Language :: Python :: 3
Requires-Dist: colorama (>=0.4.6,<0.5.0)
Requires-Dist: colorlog (>=6.8.2,<7.0.0)
Requires-Dist: deprecation (>=2.1.0,<3.0.0)
Requires-Dist: numpy (>=1.26.4,<2.0.0)
Requires-Dist: pandas (>=2.2.2,<3.0.0)
Requires-Dist: progressbar (>=2.5,<3.0)
Requires-Dist: pyfiglet (>=1.0.2,<2.0.0)
Requires-Dist: pyyaml (>=6.0.1,<7.0.0)
Requires-Dist: recpack (>=0.3.6,<0.4.0)
Requires-Dist: scikit-learn (>=1.4.1.post1,<2.0.0)
Requires-Dist: tqdm (>=4.66.4,<5.0.0)
Requires-Dist: typing-extensions (>=4.12.2,<5.0.0)
Requires-Dist: urllib3 (>=2.2.1,<3.0.0)
Project-URL: Documentation, https://suenalaba.github.io/streamsightv2
Project-URL: Repository, https://github.com/suenalaba/streamsightv2
Project-URL: Report, https://hdl.handle.net/10356/181114
